orgia/__init__.py
orgia/__main__.py
orgia/orgia.py
orgia/nics/__init__.py
orgia/nics/afrinic.py
orgia/nics/apnic.py
orgia/nics/arin.py
orgia/nics/engine.py
orgia/nics/lacnic.py
orgia/nics/ripe.py
orgia-0.1.1.dist-info/METADATA
orgia-0.1.1.dist-info/WHEEL
orgia-0.1.1.dist-info/entry_points.txt
orgia-0.1.1.dist-info/RECORD
