Metadata-Version: 2.4
Name: orgia
Version: 0.1.1
Summary: Use RDAP and WHOIS to find ASNs, Networks, and CIDRs about Organisations.
Project-URL: Homepage, https://github.com/sttlr/orgia
Author: sttlr
License-Expression: MIT
Keywords: asn,cidr,network,organisation,rdap,recon,whois
Classifier: License :: OSI Approved :: MIT License
Classifier: Programming Language :: Python :: 3 :: Only
Classifier: Programming Language :: Python :: 3.10
Classifier: Programming Language :: Python :: 3.11
Classifier: Programming Language :: Python :: 3.12
Classifier: Programming Language :: Python :: 3.13
Requires-Python: >=3.10
Requires-Dist: beautifulsoup4
Requires-Dist: h2
Requires-Dist: httpx
Requires-Dist: lxml
Requires-Dist: pyyaml
